contek_tusk/__init__.py
contek_tusk/app_name_resolver.py
contek_tusk/batching_config.py
contek_tusk/entry_input_normalizer.py
contek_tusk/entry_row.py
contek_tusk/env_tags_cache.py
contek_tusk/env_utils.py
contek_tusk/metric.py
contek_tusk/metric_batch.py
contek_tusk/metric_client.py
contek_tusk/metric_data.py
contek_tusk/metric_formatter.py
contek_tusk/schema.py
contek_tusk/schema_provider.py
contek_tusk/table.py
contek_tusk/time_column_cache.py
contek_tusk/counter/__init__.py
contek_tusk/counter/count_buffer.py
contek_tusk/counter/count_column_cache.py
contek_tusk/counter/count_details.py
contek_tusk/counter/tusk_counter.py
contek_tusk/heartbeat/__init__.py
contek_tusk/heartbeat/tuck_heartbeat_client.py
contek_tusk/heartbeat/tuck_heartbeat_config.py
contek_tusk/logging/__init__.py
contek_tusk/logging/level_mapper.py
contek_tusk/logging/tusk_handler.py
contek_tusk/logging/tusk_logging_config.py
contek_tusk/yaml/__init__.py
contek_tusk-2.2.dist-info/LICENSE.txt
contek_tusk-2.2.dist-info/METADATA
contek_tusk-2.2.dist-info/WHEEL
contek_tusk-2.2.dist-info/top_level.txt
contek_tusk-2.2.dist-info/zip-safe
contek_tusk-2.2.dist-info/RECORD
