Metadata-Version: 2.1
Name: contek-tusk
Version: 2.2
Summary: Tusk for Clickhouse metric writing
Home-page: https://github.com/contek-io/contek-tusk
Author: contek_bjy
Author-email: bjy@contek.io
License: MIT
Platform: UNKNOWN
Classifier: Programming Language :: Python :: 3
Classifier: License :: OSI Approved :: MIT License
Classifier: Operating System :: OS Independent
Requires-Python: >=3.6
License-File: LICENSE.txt
Requires-Dist: clickhouse-driver (>=0.2.5)
Requires-Dist: pandas
Requires-Dist: pyyaml
